counts/__init__.py
counts/admin.py
counts/apps.py
counts/static/css/counts/bethany_ds.css
counts/static/css/counts/medicio_ds.css
counts/static/css/counts/medilab_ds.css
counts/static/css/counts/mentor_ds.css
counts/templates/counts/_common.html
counts/templates/counts/bethany_ds.html
counts/templates/counts/medicio_ds.html
counts/templates/counts/medilab_ds.html
counts/templates/counts/mentor_ds.html
counts/templatetags/__init__.py
counts/templatetags/counts_tags.py
django_counts_ds-1.1.1.dist-info/LICENSE
django_counts_ds-1.1.1.dist-info/METADATA
django_counts_ds-1.1.1.dist-info/WHEEL
django_counts_ds-1.1.1.dist-info/top_level.txt
django_counts_ds-1.1.1.dist-info/RECORD
